bicubic_pytorch/__init__.py
bicubic_pytorch/core.py
bicubic_pytorch/test.py
bicubic_pytorch/test_gradient.py
bicubic_pytorch/utils.py
bicubic_pytorch-0.1.2.1.dist-info/licenses/LICENSE
bicubic_pytorch-0.1.2.1.dist-info/METADATA
bicubic_pytorch-0.1.2.1.dist-info/WHEEL
bicubic_pytorch-0.1.2.1.dist-info/top_level.txt
bicubic_pytorch-0.1.2.1.dist-info/RECORD
